probscale/__init__.py
probscale/algo.py
probscale/formatters.py
probscale/probscale.py
probscale/transforms.py
probscale/validate.py
probscale/viz.py
probscale/tests/__init__.py
probscale/tests/helpers.py
probscale/tests/test_algo.py
probscale/tests/test_formatters.py
probscale/tests/test_probscale.py
probscale/tests/test_transforms.py
probscale/tests/test_validate.py
probscale/tests/test_viz.py
probscale/tests/baseline_images/__init__.py
probscale/tests/baseline_images/test_probscale/__init__.py
probscale/tests/baseline_images/test_probscale/test_the_scale_beta.png
probscale/tests/baseline_images/test_probscale/test_the_scale_default.png
probscale/tests/baseline_images/test_probscale/test_the_scale_not_as_pct.png
probscale/tests/baseline_images/test_viz/__init__.py
probscale/tests/baseline_images/test_viz/test_probplot_beta_dist_best_fit_x.png
probscale/tests/baseline_images/test_viz/test_probplot_beta_dist_best_fit_y.png
probscale/tests/baseline_images/test_viz/test_probplot_color_and_label.png
probscale/tests/baseline_images/test_viz/test_probplot_pp.png
probscale/tests/baseline_images/test_viz/test_probplot_pp_bestfit.png
probscale/tests/baseline_images/test_viz/test_probplot_pp_bestfit_probax_y.png
probscale/tests/baseline_images/test_viz/test_probplot_pp_probax_y.png
probscale/tests/baseline_images/test_viz/test_probplot_prob.png
probscale/tests/baseline_images/test_viz/test_probplot_prob_bestfit.png
probscale/tests/baseline_images/test_viz/test_probplot_prob_bestfit_exceedance.png
probscale/tests/baseline_images/test_viz/test_probplot_prob_bestfit_probax_y.png
probscale/tests/baseline_images/test_viz/test_probplot_prob_probax_y.png
probscale/tests/baseline_images/test_viz/test_probplot_qq.png
probscale/tests/baseline_images/test_viz/test_probplot_qq_bestfit.png
probscale/tests/baseline_images/test_viz/test_probplot_qq_bestfit_probax_y.png
probscale/tests/baseline_images/test_viz/test_probplot_qq_dist.png
probscale-0.2.5.dist-info/LICENSE
probscale-0.2.5.dist-info/METADATA
probscale-0.2.5.dist-info/WHEEL
probscale-0.2.5.dist-info/top_level.txt
probscale-0.2.5.dist-info/RECORD
